{
  "employee": [
    {
      "name": "Puneshwar Londhe",
      "email": "punes1709@gmail.com",
      "phone": "5565555555",
      "address": "Mumbai",
      "Designation": "dmvd",
      "Packege": "12LPA",
      "companyName": "wipro",
      "id": "7688"
    },
    {
      "name": "nikhil",
      "email": "ni@gmail.com",
      "phone": "5556555555",
      "address": "pune",
      "Designation": "hh",
      "Packege": "11LPA",
      "companyName": "kotak",
      "id": "5cd3"
    },
    {
      "id": "635b",
      "name": "rajty",
      "email": "r@gmai.com",
      "phone": "5665556655",
      "address": "kg",
      "Designation": "bg",
      "Packege": "5LPA",
      "companyName": "kotak"
    },
    {
      "name": "rakesh",
      "email": "ra@gmail.com",
      "phone": "5565544999",
      "address": "nashik",
      "Designation": "ufubkdwb",
      "Packege": "7LPA",
      "companyName": "TCS",
      "id": "26ac"
    }
  ],
  "company": [
    {
      "id": "460d",
      "companyName": "kotak",
      "contact": "9856218746",
      "address": "mumbai",
      "section": "banking",
      "email": "kotak@gmail.com"
    },
    {
      "id": "17af",
      "companyName": "TCS",
      "contact": "9856294444",
      "address": "pune",
      "section": "IT",
      "email": "tcs@gmail.com"
    }
  ],
  "admin": [
    {
      "id": "8c7b",
      "Name": "akshy",
      "contact": "9021515230",
      "email": "admin1@gmail.com",
      "companyName": "kotak",
      "password": "12345678",
      "roll": "admin",
      "rollId": "2"
    },
    {
      "id": "b228",
      "Name": "punesh",
      "contact": "9856294444",
      "email": "admin2@gmail.com",
      "companyName": "TCS",
      "password": "12345678",
      "roll": "admin",
      "rollId": "2"
    }
  ],
  "superadmin": [
    {
      "name": "Cody Fisher",
      "email": "superadmin@gmail.com",
      "phone": "908908767",
      "roll": "superadmin",
      "rollId": "1",
      "password": "12345678",
      "id": "631b"
    }
  ]
}